fanpy/__init__.py
fanpy/ansi.py
fanpy/api.py
fanpy/archiver.py
fanpy/auth.py
fanpy/cli.py
fanpy/fanfou_globals.py
fanpy/logger.py
fanpy/oauth.py
fanpy/oauth_dance.py
fanpy/util.py
fanpy-0.2.0.dist-info/DESCRIPTION.rst
fanpy-0.2.0.dist-info/METADATA
fanpy-0.2.0.dist-info/RECORD
fanpy-0.2.0.dist-info/WHEEL
fanpy-0.2.0.dist-info/entry_points.txt
fanpy-0.2.0.dist-info/metadata.json
fanpy-0.2.0.dist-info/top_level.txt
